mysudoku/__init__.py
mysudoku/sudoku.py
mysudoku-1.3.dist-info/LICENSE
mysudoku-1.3.dist-info/METADATA
mysudoku-1.3.dist-info/WHEEL
mysudoku-1.3.dist-info/top_level.txt
mysudoku-1.3.dist-info/RECORD
