Metadata-Version: 2.1
Name: mysudoku
Version: 1.3
Summary: A Sudoku generator and solver
Home-page: UNKNOWN
Author: Murtada Altarouti
Author-email: murtada.altarouti@gmail.com
License: UNKNOWN
Platform: UNKNOWN
License-File: LICENSE
